miblab_plot/__init__.py
miblab_plot/image_3d.py
miblab_plot-0.0.1.dist-info/licenses/LICENSE
miblab_plot-0.0.1.dist-info/METADATA
miblab_plot-0.0.1.dist-info/WHEEL
miblab_plot-0.0.1.dist-info/top_level.txt
miblab_plot-0.0.1.dist-info/RECORD
