Metadata-Version: 2.4
Name: miblab-plot
Version: 0.0.1
Summary: Plotting utilities for medical images
Author-email: Steven Sourbron <s.sourbron@sheffield.ac.uk>
License-Expression: Apache-2.0
Project-URL: Homepage, https://miblab.org/
Project-URL: Source Code, https://github.com/openmiblab/miblab-plot
Keywords: python,medical imaging,MRI
Classifier: Development Status :: 3 - Alpha
Classifier: Intended Audience :: Developers
Classifier: Intended Audience :: Science/Research
Classifier: Topic :: Scientific/Engineering
Classifier: Operating System :: OS Independent
Classifier: Programming Language :: Python
Classifier: Programming Language :: Python :: 3
License-File: LICENSE
Requires-Dist: pillow
Requires-Dist: numpy
Requires-Dist: matplotlib
Requires-Dist: tqdm
Dynamic: license-file
